easypruner/__init__.py
easypruner/fastpruner.py
easypruner/test.py
easypruner/core/__init__.py
easypruner/core/registry.py
easypruner/prune/__init__.py
easypruner/prune/arch/DDPG.py
easypruner/prune/arch/EagleEye.py
easypruner/prune/arch/__init__.py
easypruner/prune/arch/uniform.py
easypruner/prune/importance/__init__.py
easypruner/prune/importance/criterion.py
easypruner/prune/threshold/__init__.py
easypruner/prune/utils/__init__.py
easypruner/prune_algorithm/__init__.py
easypruner/regularize/__init__.py
easypruner/regularize/sparsity.py
easypruner/utils/__init__.py
easypruner/utils/flops_counter.py
easypruner/utils/get_prune_layer.py
easypruner/utils/judge.py
easypruner/utils/prune.py
easypruner/utils/rebuild.py
easypruner-1.0.0.dist-info/LICENSE
easypruner-1.0.0.dist-info/METADATA
easypruner-1.0.0.dist-info/WHEEL
easypruner-1.0.0.dist-info/top_level.txt
easypruner-1.0.0.dist-info/RECORD
