Metadata-Version: 2.1
Name: easypruner
Version: 1.0.0
Summary: A small example package
Home-page: https://gitee.com/casia_iva_engineer/pruning-tools/tree/master/easypruner
Author: zhaoxu,jiangnanfei
Author-email: xu.zhao@nlpr.ia.ac.cn
License: BSD License
Platform: all
Classifier: Intended Audience :: Developers
Classifier: Operating System :: OS Independent
Classifier: Natural Language :: Chinese (Simplified)
Classifier: Programming Language :: Python
Classifier: Programming Language :: Python :: 2
Classifier: Programming Language :: Python :: 2.7
Classifier: Programming Language :: Python :: 3
Classifier: Programming Language :: Python :: 3.5
Classifier: Programming Language :: Python :: 3.6
Classifier: Programming Language :: Python :: 3.7
Classifier: Programming Language :: Python :: 3.8
Classifier: Topic :: Software Development :: Libraries
License-File: LICENSE
